{
    "real_balance": {
        "USD": 989.7631222121302,
        "USDC": 1001.0548256635352,
        "EUR": 1000.219890875341,
        "USDT": 1000
    },
    "loaned_balance": {},
    "positions": {
        "ETH/EUR": {
            "long": 0.0,
            "short": 0,
            "long_entry_price": null,
            "short_entry_price": null
        },
        "SHIB/USD": {
            "long": 0.0,
            "short": 4723665.564478035,
            "long_entry_price": null,
            "short_entry_price": 2.124e-05
        },
        "BCH/USD": {
            "long": 0.0,
            "short": 0.0,
            "long_entry_price": null,
            "short_entry_price": null
        },
        "LINK/USD": {
            "long": 0.0,
            "short": 0.0,
            "long_entry_price": null,
            "short_entry_price": null
        },
        "UNI/USD": {
            "long": 0.0,
            "short": 0.0,
            "long_entry_price": null,
            "short_entry_price": null
        },
        "POL/USD": {
            "long": 215.57299301543503,
            "short": 0.0,
            "long_entry_price": 0.46388,
            "short_entry_price": null
        },
        "ATOM/USD": {
            "long": 0.0,
            "short": 0,
            "long_entry_price": null,
            "short_entry_price": null
        },
        "AVAX/USD": {
            "long": 0.0,
            "short": 0.0,
            "long_entry_price": null,
            "short_entry_price": null
        },
        "DOT/USD": {
            "long": 0.0,
            "short": 0,
            "long_entry_price": null,
            "short_entry_price": null
        },
        "APE/USD": {
            "long": 0.0,
            "short": 1.4210854715202004e-14,
            "long_entry_price": null,
            "short_entry_price": 1.2311
        },
        "ADA/USD": {
            "long": 0.0,
            "short": 0,
            "long_entry_price": null,
            "short_entry_price": null
        },
        "LTC/USDC": {
            "long": 0.0,
            "short": 0.0,
            "long_entry_price": null,
            "short_entry_price": null
        },
        "DOGE/USD": {
            "long": 0,
            "short": 0.0,
            "long_entry_price": null,
            "short_entry_price": null
        }
    },
    "orders": [
        {
            "symbol": "ETH/EUR",
            "side": "buy",
            "amount": 0.031249902344055173,
            "price": 3200.01,
            "fee": 0.1,
            "created_at": "2024-12-31T04:58:08.202934"
        },
        {
            "symbol": "SHIB/USD",
            "side": "buy",
            "amount": 4852013.58563804,
            "price": 2.061e-05,
            "fee": 0.1,
            "created_at": "2024-12-31T05:04:11.753530"
        },
        {
            "symbol": "SHIB/USD",
            "side": "long",
            "amount": 4852013.58563804,
            "price": 2.069e-05,
            "pnl": 0.2877729257641884,
            "created_at": "2024-12-31T05:05:54.423448"
        },
        {
            "symbol": "BCH/USD",
            "side": "buy",
            "amount": 0.23083492994159877,
            "price": 433.21,
            "fee": 0.1,
            "created_at": "2024-12-31T05:05:54.761695"
        },
        {
            "symbol": "BCH/USD",
            "side": "long",
            "amount": 0.23083492994159877,
            "price": 434.91,
            "pnl": 0.2920269615198277,
            "created_at": "2024-12-31T05:11:44.569456"
        },
        {
            "symbol": "LINK/USD",
            "side": "sell",
            "amount": 4.938271604938271,
            "price": 20.31858,
            "fee": 0.10033866666666667,
            "created_at": "2024-12-31T05:15:20.450758"
        },
        {
            "symbol": "LINK/USD",
            "side": "short",
            "amount": 4.938271604938271,
            "price": 20.25,
            "pnl": 0.23866666666667033,
            "created_at": "2024-12-31T05:15:31.076408"
        },
        {
            "symbol": "UNI/USD",
            "side": "sell",
            "amount": 7.578053955744165,
            "price": 13.242,
            "fee": 0.10034859048196423,
            "created_at": "2024-12-31T05:15:39.632272"
        },
        {
            "symbol": "UNI/USD",
            "side": "short",
            "amount": 7.578053955744165,
            "price": 13.212,
            "pnl": 0.12722036980904167,
            "created_at": "2024-12-31T05:21:52.414341"
        },
        {
            "symbol": "POL/USD",
            "side": "buy",
            "amount": 222.64276967605477,
            "price": 0.44915,
            "fee": 0.1,
            "created_at": "2024-12-31T05:21:53.293537"
        },
        {
            "symbol": "POL/USD",
            "side": "long",
            "amount": 222.64276967605477,
            "price": 0.45161,
            "pnl": 0.4471535121896955,
            "created_at": "2024-12-31T05:27:11.086288"
        },
        {
            "symbol": "ATOM/USD",
            "side": "buy",
            "amount": 16.186468112657817,
            "price": 6.178,
            "fee": 0.09999999999999999,
            "created_at": "2024-12-31T05:27:57.769929"
        },
        {
            "symbol": "ETH/EUR",
            "side": "long",
            "amount": 0.031249902344055173,
            "price": 3213.46,
            "pnl": 0.31989087534100885,
            "created_at": "2024-12-31T05:41:09.371515"
        },
        {
            "symbol": "BCH/USD",
            "side": "buy",
            "amount": 0.22958422297219735,
            "price": 435.57,
            "fee": 0.1,
            "created_at": "2024-12-31T05:41:09.756525"
        },
        {
            "symbol": "ATOM/USD",
            "side": "long",
            "amount": 16.186468112657817,
            "price": 6.2224,
            "pnl": 0.6179605050178122,
            "created_at": "2024-12-31T05:41:39.776359"
        },
        {
            "symbol": "SHIB/USD",
            "side": "sell",
            "amount": 4854368.932038835,
            "price": 2.067e-05,
            "fee": 0.10033980582524273,
            "created_at": "2024-12-31T05:48:51.963654"
        },
        {
            "symbol": "SHIB/USD",
            "side": "short",
            "amount": 4854368.932038835,
            "price": 2.06e-05,
            "pnl": 0.23980582524272345,
            "created_at": "2024-12-31T05:49:02.049880"
        },
        {
            "symbol": "BCH/USD",
            "side": "buy",
            "amount": 0.22958422297219735,
            "price": 435.57,
            "fee": 0.1,
            "created_at": "2024-12-31T05:55:16.627685"
        },
        {
            "symbol": "BCH/USD",
            "side": "long",
            "amount": 0.22958422297219735,
            "price": 438.42,
            "pnl": 0.5536607204352969,
            "created_at": "2024-12-31T05:55:32.955890"
        },
        {
            "symbol": "UNI/USD",
            "side": "buy",
            "amount": 7.575757575757576,
            "price": 13.2,
            "fee": 0.1,
            "created_at": "2024-12-31T05:55:51.803807"
        },
        {
            "symbol": "BCH/USD",
            "side": "long",
            "amount": 0.22958422297219735,
            "price": 438.07,
            "pnl": 0.47338659687306284,
            "created_at": "2024-12-31T05:57:21.575718"
        },
        {
            "symbol": "UNI/USD",
            "side": "buy",
            "amount": 7.575757575757576,
            "price": 13.2,
            "fee": 0.1,
            "created_at": "2024-12-31T05:57:22.737240"
        },
        {
            "symbol": "UNI/USD",
            "side": "long",
            "amount": 7.575757575757576,
            "price": 13.225,
            "pnl": 0.08920454545454815,
            "created_at": "2024-12-31T06:01:22.212968"
        },
        {
            "symbol": "AVAX/USD",
            "side": "sell",
            "amount": 2.855511136493432,
            "price": 35.14,
            "fee": 0.10034266133637922,
            "created_at": "2024-12-31T06:02:00.353211"
        },
        {
            "symbol": "UNI/USD",
            "side": "long",
            "amount": 7.575757575757576,
            "price": 13.214,
            "pnl": 0.0059545454545539556,
            "created_at": "2024-12-31T06:02:10.493660"
        },
        {
            "symbol": "DOT/USD",
            "side": "buy",
            "amount": 15.233916792346479,
            "price": 6.5643,
            "fee": 0.1,
            "created_at": "2024-12-31T06:02:47.032225"
        },
        {
            "symbol": "AVAX/USD",
            "side": "short",
            "amount": 2.855511136493432,
            "price": 35.14,
            "pnl": -0.10034266133637922,
            "created_at": "2024-12-31T06:09:24.206920"
        },
        {
            "symbol": "UNI/USD",
            "side": "buy",
            "amount": 7.555152614082804,
            "price": 13.236,
            "fee": 0.1,
            "created_at": "2024-12-31T06:09:26.557672"
        },
        {
            "symbol": "UNI/USD",
            "side": "long",
            "amount": 7.555152614082804,
            "price": 13.311,
            "pnl": 0.46606980961014866,
            "created_at": "2024-12-31T06:09:51.849550"
        },
        {
            "symbol": "BCH/USD",
            "side": "buy",
            "amount": 0.22837828579258684,
            "price": 437.87,
            "fee": 0.1,
            "created_at": "2024-12-31T06:09:51.852550"
        },
        {
            "symbol": "DOT/USD",
            "side": "long",
            "amount": 15.233916792346479,
            "price": 6.627,
            "pnl": 0.854211416297237,
            "created_at": "2024-12-31T06:10:24.309040"
        },
        {
            "symbol": "POL/USD",
            "side": "buy",
            "amount": 220.5947233742169,
            "price": 0.45332,
            "fee": 0.1,
            "created_at": "2024-12-31T06:10:24.318041"
        },
        {
            "symbol": "BCH/USD",
            "side": "long",
            "amount": 0.22837828579258684,
            "price": 439.98,
            "pnl": 0.381396304839339,
            "created_at": "2024-12-31T06:11:39.589200"
        },
        {
            "symbol": "POL/USD",
            "side": "buy",
            "amount": 220.5947233742169,
            "price": 0.45332,
            "fee": 0.1,
            "created_at": "2024-12-31T06:11:40.313163"
        },
        {
            "symbol": "POL/USD",
            "side": "long",
            "amount": 220.5947233742169,
            "price": 0.45527,
            "pnl": 0.32972955086914485,
            "created_at": "2024-12-31T06:30:12.267263"
        },
        {
            "symbol": "SHIB/USD",
            "side": "buy",
            "amount": 4847309.7430925835,
            "price": 2.063e-05,
            "fee": 0.1,
            "created_at": "2024-12-31T06:30:12.593903"
        },
        {
            "symbol": "SHIB/USD",
            "side": "long",
            "amount": 4847309.7430925835,
            "price": 2.068e-05,
            "pnl": 0.14212312166746402,
            "created_at": "2024-12-31T06:32:39.009385"
        },
        {
            "symbol": "APE/USD",
            "side": "sell",
            "amount": 83.12551953449709,
            "price": 1.209,
            "fee": 0.10049875311720699,
            "created_at": "2024-12-31T06:32:40.795494"
        },
        {
            "symbol": "APE/USD",
            "side": "short",
            "amount": 83.12551953449709,
            "price": 1.1971,
            "pnl": 0.8896841230257706,
            "created_at": "2024-12-31T06:40:47.270354"
        },
        {
            "symbol": "UNI/USD",
            "side": "sell",
            "amount": 7.558007709167863,
            "price": 13.314,
            "fee": 0.10062731463986092,
            "created_at": "2024-12-31T06:40:47.770414"
        },
        {
            "symbol": "UNI/USD",
            "side": "short",
            "amount": 7.558007709167863,
            "price": 13.356,
            "pnl": -0.4183810747486948,
            "created_at": "2024-12-31T07:02:25.677442"
        },
        {
            "symbol": "APE/USD",
            "side": "buy",
            "amount": 83.53521009105337,
            "price": 1.1971,
            "fee": 0.1,
            "created_at": "2024-12-31T07:02:25.822755"
        },
        {
            "symbol": "APE/USD",
            "side": "long",
            "amount": 83.53521009105337,
            "price": 1.209,
            "pnl": 0.8930749310834534,
            "created_at": "2024-12-31T07:03:32.344635"
        },
        {
            "symbol": "POL/USD",
            "side": "buy",
            "amount": 219.61128802020426,
            "price": 0.45535,
            "fee": 0.1,
            "created_at": "2024-12-31T07:03:47.188705"
        },
        {
            "symbol": "POL/USD",
            "side": "long",
            "amount": 219.61128802020426,
            "price": 0.45677,
            "pnl": 0.6573470956407178,
            "created_at": "2024-12-31T07:04:58.265838"
        },
        {
            "symbol": "POL/USD",
            "side": "long",
            "amount": 220.59472337421687,
            "price": 0.45677,
            "pnl": 0.6602907438454091,
            "created_at": "2024-12-31T07:09:00.390886"
        },
        {
            "symbol": "ADA/USD",
            "side": "buy",
            "amount": 118.71127044801634,
            "price": 0.84238,
            "fee": 0.1,
            "created_at": "2024-12-31T07:10:27.275173"
        },
        {
            "symbol": "LINK/USD",
            "side": "buy",
            "amount": 4.9229484719906385,
            "price": 20.31303,
            "fee": 0.1,
            "created_at": "2024-12-31T07:10:33.448510"
        },
        {
            "symbol": "LINK/USD",
            "side": "long",
            "amount": 4.9229484719906385,
            "price": 20.36559,
            "pnl": 0.1584914215161387,
            "created_at": "2024-12-31T07:14:06.795227"
        },
        {
            "symbol": "APE/USD",
            "side": "sell",
            "amount": 83.12551953449709,
            "price": 1.209,
            "fee": 0.10049875311720699,
            "created_at": "2024-12-31T07:15:11.016175"
        },
        {
            "symbol": "ADA/USD",
            "side": "long",
            "amount": 118.71127044801634,
            "price": 0.842061,
            "pnl": -0.13783102637765252,
            "created_at": "2024-12-31T07:15:16.069307"
        },
        {
            "symbol": "APE/USD",
            "side": "sell",
            "amount": 83.05647840531562,
            "price": 1.209,
            "fee": 0.10041528239202659,
            "created_at": "2024-12-31T07:15:16.812899"
        },
        {
            "symbol": "APE/USD",
            "side": "short",
            "amount": 83.05647840531562,
            "price": 1.209,
            "pnl": -0.10041528239202659,
            "created_at": "2024-12-31T07:22:33.493046"
        },
        {
            "symbol": "BCH/USD",
            "side": "buy",
            "amount": 0.22965276501929083,
            "price": 435.44,
            "fee": 0.1,
            "created_at": "2024-12-31T07:22:33.526047"
        },
        {
            "symbol": "BCH/USD",
            "side": "long",
            "amount": 0.22965276501929083,
            "price": 438.48,
            "pnl": 0.5974462612529902,
            "created_at": "2024-12-31T07:28:46.402763"
        },
        {
            "symbol": "APE/USD",
            "side": "sell",
            "amount": 82.99443937256203,
            "price": 1.209,
            "fee": 0.1003402772014275,
            "created_at": "2024-12-31T07:31:02.426973"
        },
        {
            "symbol": "APE/USD",
            "side": "short",
            "amount": 82.99443937256203,
            "price": 1.209,
            "pnl": -0.1003402772014275,
            "created_at": "2024-12-31T07:33:01.508734"
        },
        {
            "symbol": "ADA/USD",
            "side": "buy",
            "amount": 118.42826740629069,
            "price": 0.844393,
            "fee": 0.1,
            "created_at": "2024-12-31T07:33:05.713408"
        },
        {
            "symbol": "APE/USD",
            "side": "short",
            "amount": 83.12551953449709,
            "price": 1.209,
            "pnl": -0.10049875311720699,
            "created_at": "2024-12-31T07:33:17.658038"
        },
        {
            "symbol": "UNI/USD",
            "side": "sell",
            "amount": 7.517666516313336,
            "price": 13.349,
            "fee": 0.10035333032626673,
            "created_at": "2024-12-31T07:33:29.433124"
        },
        {
            "symbol": "ADA/USD",
            "side": "long",
            "amount": 118.42826740629069,
            "price": 0.84465,
            "pnl": -0.0695943713412993,
            "created_at": "2024-12-31T07:38:12.053725"
        },
        {
            "symbol": "UNI/USD",
            "side": "sell",
            "amount": 7.529893677901268,
            "price": 13.349,
            "fee": 0.10051655070630404,
            "created_at": "2024-12-31T07:38:12.787297"
        },
        {
            "symbol": "UNI/USD",
            "side": "short",
            "amount": 15.004377604132458,
            "price": 13.278,
            "pnl": 0.8660826840657297,
            "created_at": "2024-12-31T07:46:24.467029"
        },
        {
            "symbol": "POL/USD",
            "side": "buy",
            "amount": 219.63058136214886,
            "price": 0.45531,
            "fee": 0.1,
            "created_at": "2024-12-31T07:50:40.767699"
        },
        {
            "symbol": "POL/USD",
            "side": "long",
            "amount": 219.63058136214886,
            "price": 0.4577,
            "pnl": 0.42439217236608096,
            "created_at": "2024-12-31T08:06:34.136027"
        },
        {
            "symbol": "UNI/USD",
            "side": "short",
            "amount": 0.04318259008214653,
            "price": 13.29,
            "pnl": 0.0019738761926549634,
            "created_at": "2024-12-31T08:08:16.149622"
        },
        {
            "symbol": "LTC/USDC",
            "side": "buy",
            "amount": 1.0174699591994547,
            "price": 98.283,
            "fee": 0.10000000000000002,
            "created_at": "2024-12-31T08:08:16.444569"
        },
        {
            "symbol": "APE/USD",
            "side": "sell",
            "amount": 82.50825082508251,
            "price": 1.216,
            "fee": 0.10033003300330033,
            "created_at": "2024-12-31T08:17:17.560663"
        },
        {
            "symbol": "APE/USD",
            "side": "short",
            "amount": 82.50825082508251,
            "price": 1.2191,
            "pnl": -0.9339191419141913,
            "created_at": "2024-12-31T08:20:55.215407"
        },
        {
            "symbol": "UNI/USD",
            "side": "buy",
            "amount": 7.5448921080428555,
            "price": 13.254,
            "fee": 0.1,
            "created_at": "2024-12-31T08:20:55.776619"
        },
        {
            "symbol": "UNI/USD",
            "side": "long",
            "amount": 7.5448921080428555,
            "price": 13.311,
            "pnl": 0.3296287913082872,
            "created_at": "2024-12-31T08:21:24.926395"
        },
        {
            "symbol": "BCH/USD",
            "side": "buy",
            "amount": 0.22856098006948256,
            "price": 437.52,
            "fee": 0.1,
            "created_at": "2024-12-31T08:21:25.821956"
        },
        {
            "symbol": "LTC/USDC",
            "side": "long",
            "amount": 1.0174699591994547,
            "price": 99.081,
            "pnl": 0.7111290864137255,
            "created_at": "2024-12-31T08:22:05.690727"
        },
        {
            "symbol": "BCH/USD",
            "side": "buy",
            "amount": 0.22856098006948256,
            "price": 437.52,
            "fee": 0.1,
            "created_at": "2024-12-31T08:22:05.818730"
        },
        {
            "symbol": "BCH/USD",
            "side": "long",
            "amount": 0.22856098006948256,
            "price": 440.98,
            "pnl": 0.6900301700493775,
            "created_at": "2024-12-31T08:25:09.953298"
        },
        {
            "symbol": "POL/USD",
            "side": "buy",
            "amount": 215.66132545450625,
            "price": 0.46369,
            "fee": 0.1,
            "created_at": "2024-12-31T08:27:26.353774"
        },
        {
            "symbol": "POL/USD",
            "side": "long",
            "amount": 215.66132545450625,
            "price": 0.46566,
            "pnl": 0.3244279583342378,
            "created_at": "2024-12-31T08:27:39.983742"
        },
        {
            "symbol": "UNI/USD",
            "side": "sell",
            "amount": 7.466587023071754,
            "price": 13.441,
            "fee": 0.10035839617710746,
            "created_at": "2024-12-31T08:29:06.807510"
        },
        {
            "symbol": "APE/USD",
            "side": "short",
            "amount": 1.4210854715202004e-14,
            "price": 1.2439,
            "pnl": -5.136357117407887e-16,
            "created_at": "2024-12-31T08:31:17.831601"
        },
        {
            "symbol": "POL/USD",
            "side": "buy",
            "amount": 215.14167079021536,
            "price": 0.46481,
            "fee": 0.1,
            "created_at": "2024-12-31T08:31:18.356692"
        },
        {
            "symbol": "POL/USD",
            "side": "long",
            "amount": 215.14167079021536,
            "price": 0.46723,
            "pnl": 0.42012220046900406,
            "created_at": "2024-12-31T08:31:57.792833"
        },
        {
            "symbol": "DOGE/USD",
            "side": "sell",
            "amount": 312.9596594998905,
            "price": 0.3205944,
            "fee": 0.1003331142615717,
            "created_at": "2024-12-31T08:33:19.113621"
        },
        {
            "symbol": "BCH/USD",
            "side": "long",
            "amount": 0.22856098006948256,
            "price": 445.82,
            "pnl": 1.7951590784421312,
            "created_at": "2024-12-31T08:33:19.124622"
        },
        {
            "symbol": "DOT/USD",
            "side": "buy",
            "amount": 14.76363421619866,
            "price": 6.7734,
            "fee": 0.1,
            "created_at": "2024-12-31T08:33:31.651395"
        },
        {
            "symbol": "DOGE/USD",
            "side": "short",
            "amount": 312.9596594998905,
            "price": 0.3188334,
            "pnl": 0.45133996807811877,
            "created_at": "2024-12-31T08:34:05.181264"
        },
        {
            "symbol": "APE/USD",
            "side": "buy",
            "amount": 80.34064433196755,
            "price": 1.2447,
            "fee": 0.1,
            "created_at": "2024-12-31T08:34:08.929125"
        },
        {
            "symbol": "DOT/USD",
            "side": "long",
            "amount": 14.76363421619866,
            "price": 6.7704,
            "pnl": -0.14424661174593598,
            "created_at": "2024-12-31T08:34:17.691049"
        },
        {
            "symbol": "LTC/USDC",
            "side": "sell",
            "amount": 0.9966115208291807,
            "price": 100.697,
            "fee": 0.10035579031293601,
            "created_at": "2024-12-31T08:34:20.149371"
        },
        {
            "symbol": "UNI/USD",
            "side": "short",
            "amount": 7.466587023071754,
            "price": 13.453,
            "pnl": -0.19004703949823548,
            "created_at": "2024-12-31T08:35:48.220843"
        },
        {
            "symbol": "POL/USD",
            "side": "sell",
            "amount": 215.10002151000216,
            "price": 0.46723,
            "fee": 0.1005011830501183,
            "created_at": "2024-12-31T08:35:48.358845"
        },
        {
            "symbol": "POL/USD",
            "side": "short",
            "amount": 215.10002151000216,
            "price": 0.46593,
            "pnl": 0.1794084749408406,
            "created_at": "2024-12-31T08:41:31.082920"
        },
        {
            "symbol": "LTC/USDC",
            "side": "sell",
            "amount": 0.9965122072745392,
            "price": 100.697,
            "fee": 0.10034578973592427,
            "created_at": "2024-12-31T08:41:31.459081"
        },
        {
            "symbol": "APE/USD",
            "side": "long",
            "amount": 80.34064433196755,
            "price": 1.233,
            "pnl": -1.039045553145322,
            "created_at": "2024-12-31T08:44:08.433568"
        },
        {
            "symbol": "POL/USD",
            "side": "sell",
            "amount": 215.47080370609783,
            "price": 0.46593,
            "fee": 0.10039431157078217,
            "created_at": "2024-12-31T08:44:08.750677"
        },
        {
            "symbol": "POL/USD",
            "side": "short",
            "amount": 215.47080370609783,
            "price": 0.46329,
            "pnl": 0.46901745313510695,
            "created_at": "2024-12-31T09:10:25.399292"
        },
        {
            "symbol": "BCH/USD",
            "side": "buy",
            "amount": 0.22544356020470277,
            "price": 443.57,
            "fee": 0.1,
            "created_at": "2024-12-31T09:10:25.816891"
        },
        {
            "symbol": "BCH/USD",
            "side": "long",
            "amount": 0.22544356020470277,
            "price": 446.58,
            "pnl": 0.5779065310999371,
            "created_at": "2024-12-31T09:18:07.634456"
        },
        {
            "symbol": "SHIB/USD",
            "side": "buy",
            "amount": 4748338.081671415,
            "price": 2.106e-05,
            "fee": 0.1,
            "created_at": "2024-12-31T09:18:11.875488"
        },
        {
            "symbol": "SHIB/USD",
            "side": "long",
            "amount": 4748338.081671415,
            "price": 2.113e-05,
            "pnl": 0.2320512820512708,
            "created_at": "2024-12-31T09:19:10.658837"
        },
        {
            "symbol": "AVAX/USD",
            "side": "buy",
            "amount": 2.7777777777777777,
            "price": 36.0,
            "fee": 0.1,
            "created_at": "2024-12-31T09:25:38.868481"
        },
        {
            "symbol": "LTC/USDC",
            "side": "short",
            "amount": 1.9931237281037197,
            "price": 100.697,
            "pnl": -0.2007015800488603,
            "created_at": "2024-12-31T09:29:11.595662"
        },
        {
            "symbol": "UNI/USD",
            "side": "buy",
            "amount": 7.462129691814043,
            "price": 13.401,
            "fee": 0.1,
            "created_at": "2024-12-31T09:31:48.706303"
        },
        {
            "symbol": "AVAX/USD",
            "side": "long",
            "amount": 2.7777777777777777,
            "price": 36.13,
            "pnl": 0.2607500000000071,
            "created_at": "2024-12-31T09:34:08.652996"
        },
        {
            "symbol": "POL/USD",
            "side": "buy",
            "amount": 215.44295070665288,
            "price": 0.46416,
            "fee": 0.1,
            "created_at": "2024-12-31T09:35:33.547978"
        },
        {
            "symbol": "POL/USD",
            "side": "long",
            "amount": 215.44295070665288,
            "price": 0.46553,
            "pnl": 0.19486168562564252,
            "created_at": "2024-12-31T09:47:12.420522"
        },
        {
            "symbol": "APE/USD",
            "side": "sell",
            "amount": 81.56606851549755,
            "price": 1.2308,
            "fee": 0.10039151712887437,
            "created_at": "2024-12-31T09:50:17.010976"
        },
        {
            "symbol": "APE/USD",
            "side": "short",
            "amount": 81.56606851549755,
            "price": 1.2261,
            "pnl": 0.28335236541598097,
            "created_at": "2024-12-31T09:50:59.742754"
        },
        {
            "symbol": "BCH/USD",
            "side": "sell",
            "amount": 0.22376370552696354,
            "price": 448.88,
            "fee": 0.10044305213694339,
            "created_at": "2024-12-31T09:51:42.747991"
        },
        {
            "symbol": "UNI/USD",
            "side": "long",
            "amount": 7.462129691814043,
            "price": 13.484,
            "pnl": 0.5187374076561464,
            "created_at": "2024-12-31T09:51:44.031954"
        },
        {
            "symbol": "LTC/USDC",
            "side": "buy",
            "amount": 0.9953814301640389,
            "price": 100.464,
            "fee": 0.1,
            "created_at": "2024-12-31T09:51:44.438652"
        },
        {
            "symbol": "BCH/USD",
            "side": "short",
            "amount": 0.22376370552696354,
            "price": 447.23,
            "pnl": 0.2691362720966608,
            "created_at": "2024-12-31T10:01:18.403223"
        },
        {
            "symbol": "APE/USD",
            "side": "sell",
            "amount": 81.49959250203749,
            "price": 1.2311,
            "fee": 0.10033414832925835,
            "created_at": "2024-12-31T10:07:46.187469"
        },
        {
            "symbol": "LTC/USDC",
            "side": "long",
            "amount": 0.9953814301640389,
            "price": 101.515,
            "pnl": 0.9450997372193044,
            "created_at": "2024-12-31T10:43:46.951361"
        },
        {
            "symbol": "POL/USD",
            "side": "buy",
            "amount": 215.57299301543503,
            "price": 0.46388,
            "fee": 0.1,
            "created_at": "2024-12-31T10:43:47.344405"
        },
        {
            "symbol": "APE/USD",
            "side": "short",
            "amount": 81.49959250203747,
            "price": 1.22,
            "pnl": 0.8052159739201391,
            "created_at": "2024-12-31T11:17:29.896062"
        },
        {
            "symbol": "APE/USD",
            "side": "buy",
            "amount": 81.98737394441255,
            "price": 1.2197,
            "fee": 0.09999999999999999,
            "created_at": "2024-12-31T11:30:48.580287"
        },
        {
            "symbol": "APE/USD",
            "side": "long",
            "amount": 81.98737394441255,
            "price": 1.2199,
            "pnl": -0.08361892268590818,
            "created_at": "2024-12-31T11:39:30.466398"
        },
        {
            "symbol": "UNI/USD",
            "side": "buy",
            "amount": 7.361601884570082,
            "price": 13.584,
            "fee": 0.1,
            "created_at": "2024-12-31T11:42:24.357636"
        },
        {
            "symbol": "UNI/USD",
            "side": "long",
            "amount": 7.361601884570082,
            "price": 13.618,
            "pnl": 0.15004416961131253,
            "created_at": "2024-12-31T11:46:16.372937"
        },
        {
            "symbol": "DOT/USD",
            "side": "buy",
            "amount": 14.922255051183337,
            "price": 6.7014,
            "fee": 0.1,
            "created_at": "2024-12-31T12:03:43.389582"
        },
        {
            "symbol": "DOT/USD",
            "side": "long",
            "amount": 14.922255051183337,
            "price": 6.7335,
            "pnl": 0.3785253827558523,
            "created_at": "2024-12-31T12:09:57.923480"
        },
        {
            "symbol": "SHIB/USD",
            "side": "sell",
            "amount": 4723665.564478035,
            "price": 2.124e-05,
            "fee": 0.10033065658951347,
            "created_at": "2024-12-31T12:12:38.952423"
        }
    ]
}